APS's/APS4 - Computer/lib/alu.v
/**
 * Unidade aritmética lógica de 8 bits com 2 entradas.
 *
 * É capaz de executar 4 tipos de operações aritméticas:
 * - a + b (soma)
 * - a + 1 (incremento)
 * - a - b (subtração)
 * - a - 1 (decremento)
 *
 * Também pode executar 4 tipos de operações lógicas:
 * - a and b
 * - a or b
 * - a xor b
 * - not a
 *
 * Retorna um resultado e 4 bit flags:
 * - N, indica quando o resultado representa um inteiro negativo
 * - Z, indica quando o resultado é zero
 * - V, indica se houve overflow e o resultado deve ser descartado (apenas para aritmética)
 * - C, indica o valor do carry-out de operações aritméticas
 */
module ALU8 (
    output  reg [7:0] result,
    output  reg       n, z, v, c,

    input  wire [7:0] a, b,
    input  wire [2:0] operation
);

    parameter ADD = 3'b000;
    parameter INC = 3'b001;
    parameter SUB = 3'b010;
    parameter DEC = 3'b011;
    parameter AND = 3'b100;
    parameter OR  = 3'b101;
    parameter XOR = 3'b110;
    parameter NOT = 3'b111;


    always @ (a, b, operation)
		begin
			case (operation)
				ADD: begin
							{c, result} = a + b;
							n = result[7];
							if (result==0)
								z = 1;
							else
								z = 0;
							if (a[7]==0 && b[7]==0 && result[7]==1) 
								v = 1;
							else if (a[7]==1 && b[7]==1 && result[7]==0)
								v = 1;
							else
								v = 0;
						end
				3'b001: begin
							{c, result} = a + 1;
							n = result[7];
							if (result==0)
								z = 1;
							else
								z = 0;
							if (a[7]==0 && result[7]==1) 
								v = 1;
							else
								v = 0;
						end	
				3'b010: begin
							{c, result} = a - b;
							n = result[7];
							if (result==0)
								z = 1;
							else
								z = 0;
							if (a[7]==0 && b[7]==1 && result[7]==1) 
								v = 1;
							else if (a[7]==1 && b[7]==0 && result[7]==0)
								v = 1;
							else 
								v = 0;
						end
				3'b011: begin
							{c, result} = a - 1;
							n = result[7];
							if (result==0)
								z = 1;
							else
								z = 0;
							if (a[7]==1 && result[7]==0) 
								v = 1;
							else 
								v = 0;          
						end	
				3'b100: begin
							result = a & b;
							n = result[7];
							if (result==0)
								z = 1;
							else
								z = 0;
							v = 0;
							c = 0;
						end
				3'b101: begin
							result = a | b;
							n = result[7];
							if (result==0)
								z = 1;
							else
								z = 0;
							v = 0;
							c = 0;
						end
				3'b110: begin
							result = a ^ b;
							n = result[7];
							if (result==0)
								z = 1;
							else
								z = 0;
							v = 0;
							c = 0;
						end
				3'b111: begin
							result = ~a;
							n = result[7];
							if (result==0)
								z = 1;
							else
								z = 0;
							v = 0;
							c = 0;
						end	
				default: begin
							result = 8'hXX;
							{n, z, v, c} = 4'hX; 
						end
				endcase	
		end	
    
endmodule

APS's/APS4 - Computer/lib/register.v
/** 
 * Registro de 4 bits com reset assíncrono.
 */
module REG4 (
    output reg  [3:0] reg_out,

    input  wire [3:0] reg_in,

    input  wire       enable,
                      clk,
                      reset
);
    
    always @ (posedge clk or negedge reset) 
        begin
            if (!reset)
                reg_out <= 4'h0;
            else if (enable)
                reg_out <= reg_in;
        end

endmodule


/**
 * Registro de 8 bits com reset assíncrono.
 */
module REG8 (
    output reg  [7:0] reg_out,

    input  wire [7:0] reg_in,

    input  wire       enable,
                      clk,
                      reset
);
    
    always @ (posedge clk or negedge reset) 
        begin
            if (!reset)
                reg_out <= 8'h00;
            else if (enable)
                reg_out <= reg_in;
        end

endmodule

APS's/APS4 - Computer/lib/counter.v
/** Contador de 8 bits com reset assíncrono. */
module CNT8 (
    output reg  [7:0] count,

    input  wire [7:0] count_in,

    input  wire       load,
                      enable,
                      clk,
                      reset
);

    initial 
        begin
            count = 8'h00;
        end

    always @ (posedge clk or negedge reset) 
        begin
            if (!reset)
                count <= 8'h00;
            else if (enable)
                count <= load ? count_in : count + 1;
        end

endmodule

APS's/APS4 - Computer/data_path/data_path.v
`include "../lib/counter.v"
`include "../lib/register.v"
`include "../lib/alu.v"

/**
 * Módulo do "data path" interno à CPU, com registros internos e "data bus" de 8 bits.
 *
 * Possui 6 elementos:
 * - Registro de Instruções (IR)
 * - Registro de Endereços de Memória (MAR)
 * - Contador de Programas (PC)
 * - Registros A e B, usados para rapidamente guardar dados intermediários
 * - Unidade Aritmética-Lógica (ALU)
 * - Registro de Código de Condições (CCR)
 */
module data_path (
    output reg  [7:0] to_memory,

    output wire [7:0] address,
                      IR_out,

	output wire [3:0] CCR_Result,

    input  wire [7:0] from_memory,
    
    input  wire [2:0] ALU_Sel,

	input  wire [1:0] Bus1_Sel,
                      Bus2_Sel,

	input  wire       IR_Load, 
                      MAR_Load,
                      PC_Load,
                      PC_Inc,
                      A_Load,
                      B_Load,
                      CCR_Load,

                      clk, 
                      reset
);

    reg [7:0] bus_1, bus_2;
    
    wire [3:0] NZVC;

    wire [7:0] PC_out, 
               A_out, 
               B_out,
               ALU_Result;

    REG8 IR (
        .reg_out(IR_out), 
        .reg_in(bus_2),

        .enable(IR_Load),
        .clk(clk),
        .reset(reset)
    );

    REG8 MAR (
        .reg_out(address), 
        .reg_in(bus_2),

        .enable(MAR_Load),
        .clk(clk),
        .reset(reset)
    );

    CNT8 PC (
        .count(PC_out),

        .count_in(bus_2),

        .load(PC_Load),
        .enable(PC_Inc),
        .clk(clk),
        .reset(reset)
    );

    REG8 A (
        .reg_out(A_out), 
        .reg_in(bus_2),

        .enable(A_Load),
        .clk(clk),
        .reset(reset)
    );

    REG8 B (
        .reg_out(B_out), 
        .reg_in(bus_2),

        .enable(B_Load),
        .clk(clk),
        .reset(reset)
    );

    REG4 CCR (
        .reg_out(CCR_Result), 
        .reg_in(NZVC),

        .enable(CCR_Load),
        .clk(clk),
        .reset(reset)
    );

    ALU8 ALU (
        .result(ALU_Result),
        
        .n(NZVC[3]),
        .z(NZVC[2]),
        .v(NZVC[1]),
        .c(NZVC[0]),

        .a(A_out),
        .b(bus_1),
        .operation(ALU_Sel)
    );

    always @ (Bus1_Sel, PC_out, A_out, B_out) 
     	begin: MUX_BUS1
            case (Bus1_Sel)
                2'b00   : bus_1 = PC_out;
				2'b01   : bus_1 = A_out;
				2'b10   : bus_1 = B_out; 
				default : bus_1 = 8'hXX;
            endcase
		end

    always @ (Bus2_Sel, ALU_Result, bus_1, from_memory) 
		begin: MUX_BUS2
			case (Bus2_Sel)
				2'b00   : bus_2 = ALU_Result;
				2'b01   : bus_2 = bus_1;
				2'b10   : bus_2 = from_memory; 
				default : bus_2 = 8'hXX;
			endcase 
		end
    
    always @ (bus_1) 
	 	begin
			to_memory = bus_1;
		end

endmodule

APS's/APS4 - Computer/data_path/data_path_tb.v
`timescale 1ns/1ps
`include "data_path.v"

module data_path_tb;
    reg  [7:0] from_memory;
    reg  [2:0] ALU_Sel;
    reg  [1:0] Bus1_Sel, Bus2_Sel;
    reg        IR_Load, MAR_Load, PC_Load, PC_Inc, A_Load, B_Load, CCR_Load;
    reg        clk, reset;

    wire [7:0] to_memory;
    wire [7:0] address, IR_out;
    wire [3:0] CCR_Result;

    // DUT
    data_path dut (
        .to_memory(to_memory),
        .address(address),
        .IR_out(IR_out),
        .CCR_Result(CCR_Result),
        .from_memory(from_memory),
        .ALU_Sel(ALU_Sel),
        .Bus1_Sel(Bus1_Sel),
        .Bus2_Sel(Bus2_Sel),
        .IR_Load(IR_Load),
        .MAR_Load(MAR_Load),
        .PC_Load(PC_Load),
        .PC_Inc(PC_Inc),
        .A_Load(A_Load),
        .B_Load(B_Load),
        .CCR_Load(CCR_Load),
        .clk(clk),
        .reset(reset)
    );

    // Clock
    always #5 clk = ~clk;

    // Task para reset
    task reset_dut;
    begin
        reset = 0;
        #10;
        reset = 1;
    end
    endtask

    initial begin
        $dumpfile("data_path.vcd");
        $dumpvars(0, data_path_tb);

        clk = 0;
        reset_dut();

        // ================================
        // (i) Carregar registros from_memory
        // ================================
        from_memory = 8'hAA;
        Bus2_Sel = 2'b10; // from_memory -> bus2
        IR_Load = 1; #10; IR_Load = 0;   // Carrega IR
        MAR_Load = 1; #10; MAR_Load = 0; // Carrega MAR
        A_Load = 1; #10; A_Load = 0;     // Carrega A
        B_Load = 1; #10; B_Load = 0;     // Carrega B
        PC_Inc = 1; PC_Load = 1; #10; PC_Load = 0; PC_Inc = 0;   // Carrega PC

        // ================================
        // (ii) PC, A ou B -> to_memory via Bus1
        // ================================
        Bus1_Sel = 2'b00; #10; // PC -> to_memory
        Bus1_Sel = 2'b01; #10; // A -> to_memory
        Bus1_Sel = 2'b10; #10; // B -> to_memory

        // ================================
        // (iii) ALU operações
        // ================================
        Bus2_Sel = 2'b10; from_memory = 8'h05; A_Load = 1; #10; A_Load = 0; // A=0x05
        from_memory = 8'h03; B_Load = 1; #10; B_Load = 0; // B=0x03

        Bus2_Sel = 2'b00; // ALU -> bus2
        ALU_Sel = 3'b000; CCR_Load = 1; #10; // ADD
        ALU_Sel = 3'b010; #10; // SUB
        ALU_Sel = 3'b100; #10; // AND
        ALU_Sel = 3'b101; #10; // OR
        CCR_Load = 0;

        // ================================
        // (iv) MAR carregado e visível em address
        // ================================
        from_memory = 8'h55;
        Bus2_Sel = 2'b10; MAR_Load = 1; #10; MAR_Load = 0;

        #50;
        $finish;
    end
endmodule

APS's/APS4 - Computer/data_path/data_path.vcd
$date
	Sun Aug 10 12:01:15 2025
$end
$version
	Icarus Verilog
$end
$timescale
	1ps
$end
$scope module data_path_tb $end
$var wire 8 ! to_memory [7:0] $end
$var wire 8 " address [7:0] $end
$var wire 8 # IR_out [7:0] $end
$var wire 4 $ CCR_Result [3:0] $end
$var reg 3 % ALU_Sel [2:0] $end
$var reg 1 & A_Load $end
$var reg 1 ' B_Load $end
$var reg 2 ( Bus1_Sel [1:0] $end
$var reg 2 ) Bus2_Sel [1:0] $end
$var reg 1 * CCR_Load $end
$var reg 1 + IR_Load $end
$var reg 1 , MAR_Load $end
$var reg 1 - PC_Inc $end
$var reg 1 . PC_Load $end
$var reg 1 / clk $end
$var reg 8 0 from_memory [7:0] $end
$var reg 1 1 reset $end
$scope module dut $end
$var wire 3 2 ALU_Sel [2:0] $end
$var wire 1 & A_Load $end
$var wire 1 ' B_Load $end
$var wire 2 3 Bus1_Sel [1:0] $end
$var wire 2 4 Bus2_Sel [1:0] $end
$var wire 1 * CCR_Load $end
$var wire 1 + IR_Load $end
$var wire 1 , MAR_Load $end
$var wire 1 - PC_Inc $end
$var wire 1 . PC_Load $end
$var wire 1 / clk $end
$var wire 8 5 from_memory [7:0] $end
$var wire 1 1 reset $end
$var wire 8 6 address [7:0] $end
$var wire 8 7 PC_out [7:0] $end
$var wire 4 8 NZVC [3:0] $end
$var wire 8 9 IR_out [7:0] $end
$var wire 4 : CCR_Result [3:0] $end
$var wire 8 ; B_out [7:0] $end
$var wire 8 < A_out [7:0] $end
$var wire 8 = ALU_Result [7:0] $end
$var reg 8 > bus_1 [7:0] $end
$var reg 8 ? bus_2 [7:0] $end
$var reg 8 @ to_memory [7:0] $end
$scope module A $end
$var wire 1 / clk $end
$var wire 1 & enable $end
$var wire 8 A reg_in [7:0] $end
$var wire 1 1 reset $end
$var reg 8 B reg_out [7:0] $end
$upscope $end
$scope module ALU $end
$var wire 8 C a [7:0] $end
$var wire 3 D operation [2:0] $end
$var wire 8 E b [7:0] $end
$var parameter 3 F ADD $end
$var parameter 3 G AND $end
$var parameter 3 H DEC $end
$var parameter 3 I INC $end
$var parameter 3 J NOT $end
$var parameter 3 K OR $end
$var parameter 3 L SUB $end
$var parameter 3 M XOR $end
$var reg 1 N c $end
$var reg 1 O n $end
$var reg 8 P result [7:0] $end
$var reg 1 Q v $end
$var reg 1 R z $end
$upscope $end
$scope module B $end
$var wire 1 / clk $end
$var wire 1 ' enable $end
$var wire 8 S reg_in [7:0] $end
$var wire 1 1 reset $end
$var reg 8 T reg_out [7:0] $end
$upscope $end
$scope module CCR $end
$var wire 1 / clk $end
$var wire 1 * enable $end
$var wire 4 U reg_in [3:0] $end
$var wire 1 1 reset $end
$var reg 4 V reg_out [3:0] $end
$upscope $end
$scope module IR $end
$var wire 1 / clk $end
$var wire 1 + enable $end
$var wire 8 W reg_in [7:0] $end
$var wire 1 1 reset $end
$var reg 8 X reg_out [7:0] $end
$upscope $end
$scope module MAR $end
$var wire 1 / clk $end
$var wire 1 , enable $end
$var wire 8 Y reg_in [7:0] $end
$var wire 1 1 reset $end
$var reg 8 Z reg_out [7:0] $end
$upscope $end
$scope module PC $end
$var wire 1 / clk $end
$var wire 8 [ count_in [7:0] $end
$var wire 1 - enable $end
$var wire 1 . load $end
$var wire 1 1 reset $end
$var reg 8 \ count [7:0] $end
$upscope $end
$scope begin MUX_BUS1 $end
$upscope $end
$scope begin MUX_BUS2 $end
$upscope $end
$upscope $end
$scope task reset_dut $end
$upscope $end
$upscope $end
$enddefinitions $end
$comment Show the parameter values. $end
$dumpall
b110 M
b10 L
b101 K
b111 J
b1 I
b11 H
b100 G
b0 F
$end
#0
$dumpvars
b0 \
bx [
b0 Z
bx Y
b0 X
bx W
b0 V
bx U
b0 T
bx S
xR
xQ
bx P
xO
xN
b0 E
bx D
b0 C
b0 B
bx A
bx @
bx ?
bx >
bx =
b0 <
b0 ;
b0 :
b0 9
bx 8
b0 7
b0 6
bx 5
bx 4
bx 3
bx 2
01
bx 0
0/
x.
x-
x,
x+
x*
bx )
bx (
x'
x&
bx %
b0 $
b0 #
b0 "
bx !
$end
#5000
1/
#10000
b10101010 ?
b10101010 A
b10101010 S
b10101010 W
b10101010 Y
b10101010 [
0/
1+
b10 )
b10 4
b10101010 0
b10101010 5
11
#15000
b10101010 #
b10101010 9
b10101010 X
1/
#20000
0/
1,
0+
#25000
b10101010 "
b10101010 6
b10101010 Z
1/
#30000
0/
1&
0,
#35000
b10101010 <
b10101010 B
b10101010 C
1/
#40000
0/
1'
0&
#45000
b10101010 ;
b10101010 E
b10101010 T
1/
#50000
0/
1.
0'
#55000
1/
#60000
b0 !
b0 @
b0 >
0/
b0 (
b0 3
0.
#65000
1/
#70000
b10101010 !
b10101010 @
b10101010 >
0/
b1 (
b1 3
#75000
1/
#80000
0/
b10 (
b10 3
#85000
1/
#90000
b101 ?
b101 A
b101 S
b101 W
b101 Y
b101 [
0/
1&
b101 0
b101 5
#95000
b101 <
b101 B
b101 C
1/
#100000
b11 ?
b11 A
b11 S
b11 W
b11 Y
b11 [
0/
1'
b11 0
b11 5
0&
#105000
b11 !
b11 @
b11 >
b11 ;
b11 E
b11 T
1/
#110000
0Q
bx00 8
bx00 U
0N
b1000 =
b1000 P
b1000 ?
b1000 A
b1000 S
b1000 W
b1000 Y
b1000 [
0/
1*
b0 %
b0 2
b0 D
b0 )
b0 4
0'
#115000
bx00 $
bx00 :
bx00 V
1/
#120000
b10 ?
b10 A
b10 S
b10 W
b10 Y
b10 [
b10 =
b10 P
0R
b0 8
b0 U
0O
0/
b10 %
b10 2
b10 D
#125000
b0 $
b0 :
b0 V
1/
#130000
b1 ?
b1 A
b1 S
b1 W
b1 Y
b1 [
b1 =
b1 P
0/
b100 %
b100 2
b100 D
#135000
1/
#140000
b111 ?
b111 A
b111 S
b111 W
b111 Y
b111 [
b111 =
b111 P
0/
b101 %
b101 2
b101 D
#145000
1/
#150000
b1010101 ?
b1010101 A
b1010101 S
b1010101 W
b1010101 Y
b1010101 [
0/
1,
b10 )
b10 4
b1010101 0
b1010101 5
0*
#155000
b1010101 "
b1010101 6
b1010101 Z
1/
#160000
0/
0,
